[
null,
{"id":1,"expanded":true,"name":"NIGHT","order":22,"parentId":0,"scrollX":647.3333333333334,"scrollY":934.6666666666666},
{"id":2,"expanded":true,"name":"FATHEROOM1","order":3,"parentId":6,"scrollX":658,"scrollY":437.6666666666667},
{"id":3,"expanded":false,"name":"GIRLROOM","order":14,"parentId":4,"scrollX":665.3333333333334,"scrollY":414},
{"id":4,"expanded":true,"name":"DAY","order":1,"parentId":0,"scrollX":648.6666666666666,"scrollY":1658.6666666666667},
{"id":5,"expanded":true,"name":"BADGUYROOM","order":20,"parentId":4,"scrollX":551.3333333333334,"scrollY":474.6666666666667},
{"id":6,"expanded":false,"name":"FATHEROOM","order":2,"parentId":4,"scrollX":562,"scrollY":370.6666666666667},
{"id":7,"expanded":true,"name":"Center Room","order":4,"parentId":2,"scrollX":658,"scrollY":437.6666666666667},
{"id":8,"expanded":true,"name":"GIRLROOM1","order":15,"parentId":3,"scrollX":658,"scrollY":437.6666666666667},
{"id":9,"expanded":false,"name":"HENCHEMEN","order":16,"parentId":4,"scrollX":654.6666666666666,"scrollY":498},
{"id":10,"expanded":false,"name":"Trap","order":17,"parentId":9,"scrollX":658,"scrollY":437.6666666666667},
{"id":11,"expanded":false,"name":"BIGBUIDING","order":18,"parentId":4,"scrollX":654.6666666666666,"scrollY":1071.3333333333333},
{"id":12,"expanded":false,"name":"Slingshot","order":19,"parentId":11,"scrollX":658,"scrollY":437.6666666666667},
{"id":13,"expanded":true,"name":"UpperRoomsHallway","order":5,"parentId":7,"scrollX":658,"scrollY":437.6666666666667},
{"id":14,"expanded":false,"name":"Room2","order":6,"parentId":13,"scrollX":832,"scrollY":640},
{"id":15,"expanded":true,"name":"Room3","order":7,"parentId":13,"scrollX":658,"scrollY":437.6666666666667},
{"id":16,"expanded":true,"name":"BottomRoomsHallway","order":8,"parentId":7,"scrollX":987,"scrollY":656.5},
{"id":17,"expanded":false,"name":"Room5","order":9,"parentId":16,"scrollX":987,"scrollY":656.5},
{"id":18,"expanded":false,"name":"Room6","order":10,"parentId":16,"scrollX":987,"scrollY":656.5},
{"id":19,"expanded":true,"name":"Lightroom","order":12,"parentId":7,"scrollX":658,"scrollY":437.6666666666667},
{"id":20,"expanded":false,"name":"Room1","order":13,"parentId":7,"scrollX":987,"scrollY":656.5},
{"id":21,"expanded":false,"name":"Room4","order":11,"parentId":16,"scrollX":658,"scrollY":437.6666666666667},
{"id":22,"expanded":false,"name":"Switch","order":25,"parentId":23,"scrollX":1025.3333333333333,"scrollY":923.3333333333334},
{"id":23,"expanded":false,"name":"Underground(level 3)","order":23,"parentId":1,"scrollX":655.3333333333334,"scrollY":930.6666666666666},
{"id":24,"expanded":true,"name":"Grease","order":24,"parentId":23,"scrollX":654.6666666666666,"scrollY":546},
{"id":25,"expanded":false,"name":"ERNEST JACOBSON","order":21,"parentId":4,"scrollX":562,"scrollY":370.6666666666667}
]